Metadata-Version: 2.1
Name: boxfile
Version: 0.1.0
Summary: Fast format for storing AI training data.
Home-page: http://github.com/danijar/boxfile
Classifier: Intended Audience :: Science/Research
Classifier: License :: OSI Approved :: MIT License
Classifier: Programming Language :: Python :: 3
